pinpal/__init__.py
pinpal/app.py
pinpal/cli.py
pinpal/difficulty.py
pinpal/macos.py
pinpal/mem1.py
pinpal/mem2.py
pinpal/txtui.py
pinpal/uiboundary.py
pinpal/test/__init__.py
pinpal/test/test_mem2.py
pinpal/test/test_txtui.py
pinpal-2025.8.21.dist-info/licenses/LICENSE
pinpal-2025.8.21.dist-info/METADATA
pinpal-2025.8.21.dist-info/WHEEL
pinpal-2025.8.21.dist-info/entry_points.txt
pinpal-2025.8.21.dist-info/top_level.txt
pinpal-2025.8.21.dist-info/RECORD
