Metadata-Version: 2.4
Name: pinpal
Version: 2025.8.21
Author-email: Glyph <glyph@glyph.im>
License: The MIT License (MIT)
Project-URL: Home, https://github.com/glyph/pinpal/
Classifier: License :: OSI Approved :: MIT License
License-File: LICENSE
Requires-Dist: keyring
Requires-Dist: horsephrase
Requires-Dist: fritter
Requires-Dist: twisted
Provides-Extra: gui
Requires-Dist: py2app; sys_platform == "darwin" and extra == "gui"
Requires-Dist: pyobjc-core; sys_platform == "darwin" and extra == "gui"
Requires-Dist: pyobjc-framework-Cocoa; sys_platform == "darwin" and extra == "gui"
Requires-Dist: pyobjc-framework-ExceptionHandling; sys_platform == "darwin" and extra == "gui"
Requires-Dist: pyobjc-framework-UserNotifications; sys_platform == "darwin" and extra == "gui"
Requires-Dist: pyobjc-framework-CFNetwork; sys_platform == "darwin" and extra == "gui"
Requires-Dist: pyobjc-framework-ServiceManagement; sys_platform == "darwin" and extra == "gui"
Requires-Dist: quickmacapp>=2025.1.21; sys_platform == "darwin" and extra == "gui"
Requires-Dist: quickmachotkey; sys_platform == "darwin" and extra == "gui"
Requires-Dist: ewmh; sys_platform == "linux" and extra == "gui"
Requires-Dist: pycairo; sys_platform == "linux" and extra == "gui"
Requires-Dist: PyGObject; sys_platform == "linux" and extra == "gui"
Requires-Dist: python-xlib; sys_platform == "linux" and extra == "gui"
Requires-Dist: pydbus; sys_platform == "linux" and extra == "gui"
Provides-Extra: dev
Requires-Dist: pip-tools; extra == "dev"
Requires-Dist: mypy; extra == "dev"
Requires-Dist: mypy-zope; extra == "dev"
Requires-Dist: types-python-dateutil; extra == "dev"
Requires-Dist: pygobject-stubs; extra == "dev"
Requires-Dist: types-python-xlib; extra == "dev"
Requires-Dist: encrust; sys_platform == "darwin" and extra == "dev"
Dynamic: license-file
